serchding/__init__.py
serchding/api.py
serchding/auth.py
serchding/decl.py
serchding/dump.py
serchding/search.py
serchding/serchding.py
serchding/sync.py
serchding/utils.py
serchding-1.0.6.dist-info/METADATA
serchding-1.0.6.dist-info/WHEEL
serchding-1.0.6.dist-info/entry_points.txt
serchding-1.0.6.dist-info/licenses/LICENSE
serchding-1.0.6.dist-info/RECORD
