Metadata-Version: 2.4
Name: serchding
Version: 1.0.6
Summary: Fulltext search for linkding
Author-email: Xuanli <ludwigchen@proton.me>
License-File: LICENSE
Requires-Python: >=3.12
Requires-Dist: clean-text>=0.6.0
Requires-Dist: click>=8.1.8
Requires-Dist: dacite>=1.9.2
Requires-Dist: fake-useragent>=2.0.3
Requires-Dist: html2text>=2024.2.26
Requires-Dist: requests>=2.32.3
Requires-Dist: unidecode>=1.3.8
Requires-Dist: validators>=0.34.0
Requires-Dist: whoosh-reloaded>=2.7.5
